tilia/__init__.py
tilia/pyautogui_utils.py
tilia/sap_utils.py
tilia-1.1.0.dist-info/METADATA
tilia-1.1.0.dist-info/WHEEL
tilia-1.1.0.dist-info/top_level.txt
tilia-1.1.0.dist-info/RECORD
