Metadata-Version: 2.1
Name: tilia
Version: 1.1.0
Summary: One more layer for pyautogui. Utilities for SAP integration.
Author: ralves-e
Author-email: martins.ruiafonso@gmail.com
License: MIT License
Project-URL: code, https://github.com/rafonsomartins/tilia
Project-URL: Example of Usage, https://github.com/rafonsomartins/job_rar/tree/main/Automate%20SAP%20Assessment%20Cycle
Classifier: Programming Language :: Python :: 3
Classifier: License :: OSI Approved :: MIT License
Classifier: Operating System :: OS Independent
Requires-Python: >=3.6
Requires-Dist: pyautogui
Requires-Dist: pyperclip
Requires-Dist: pygetwindow
